fallout/__init__.py
fallout/__main__.py
fallout/fallout.py
fallout-0.0.5.dist-info/METADATA
fallout-0.0.5.dist-info/WHEEL
fallout-0.0.5.dist-info/licenses/LICENSE
fallout-0.0.5.dist-info/RECORD
