Metadata-Version: 2.4
Name: fallout
Version: 0.0.5
Summary: The Fallout library provides simple methods for calculating decay times, remaining mass, and radiation dose (siverts) for a set of predefined radioactive chemicals.
Project-URL: Repository, https://github.com/qubit999/fallout
Author-email: Alexander Slatina <a.slatina@aol.com>
License: Copyright 2025 Alexander Slatina
License-File: LICENSE
Classifier: License :: OSI Approved :: MIT License
Classifier: Operating System :: OS Independent
Classifier: Programming Language :: Python :: 3
